{
  "rodada": 12,
  "tipo": "ECONOMICO",
  "atualizado_em": "2026-04-15T07:47:34.381Z",
  "dados": [
    {
      "RODADA": 12,
      "TIPO": "ECONOMICO",
      "STATUS": "TITULAR",
      "POS": "GOL",
      "NOME": "Gabriel Braz?o",
      "CLUBE": "SAN",
      "PRECO": 6.95,
      "EXP_SCORE": 3.456,
      "ATLETA_ID": 103056
    },
    {
      "RODADA": 12,
      "TIPO": "ECONOMICO",
      "STATUS": "TITULAR",
      "POS": "LAT",
      "NOME": "Ramon",
      "CLUBE": "VIT",
      "PRECO": 10.07,
      "EXP_SCORE": 5.2669,
      "ATLETA_ID": 101597
    },
    {
      "RODADA": 12,
      "TIPO": "ECONOMICO",
      "STATUS": "TITULAR",
      "POS": "LAT",
      "NOME": "Igor Vin?cius",
      "CLUBE": "SAN",
      "PRECO": 11.02,
      "EXP_SCORE": 5.5096,
      "ATLETA_ID": 95466
    },
    {
      "RODADA": 12,
      "TIPO": "ECONOMICO",
      "STATUS": "TITULAR",
      "POS": "ZAG",
      "NOME": "Cac?",
      "CLUBE": "VIT",
      "PRECO": 7.64,
      "EXP_SCORE": 2.7214,
      "ATLETA_ID": 102340
    },
    {
      "RODADA": 12,
      "TIPO": "ECONOMICO",
      "STATUS": "TITULAR",
      "POS": "ZAG",
      "NOME": "Arthur Dias",
      "CLUBE": "CAP",
      "PRECO": 6.69,
      "EXP_SCORE": 2.0855,
      "ATLETA_ID": 130843
    },
    {
      "RODADA": 12,
      "TIPO": "ECONOMICO",
      "STATUS": "TITULAR",
      "POS": "MEI",
      "NOME": "Dudu",
      "CLUBE": "CAP",
      "PRECO": 2.67,
      "EXP_SCORE": 1.7499,
      "ATLETA_ID": 125746
    },
    {
      "RODADA": 12,
      "TIPO": "ECONOMICO",
      "STATUS": "TITULAR",
      "POS": "MEI",
      "NOME": "Reinier",
      "CLUBE": "CAM",
      "PRECO": 4.77,
      "EXP_SCORE": 2.435,
      "ATLETA_ID": 105068
    },
    {
      "RODADA": 12,
      "TIPO": "ECONOMICO",
      "STATUS": "TITULAR",
      "POS": "MEI",
      "NOME": "Thiago Mendes",
      "CLUBE": "VAS",
      "PRECO": 8.37,
      "EXP_SCORE": 3.8606,
      "ATLETA_ID": 71123
    },
    {
      "RODADA": 12,
      "TIPO": "ECONOMICO",
      "STATUS": "TITULAR",
      "POS": "MEI",
      "NOME": "Savarino",
      "CLUBE": "FLU",
      "PRECO": 10.05,
      "EXP_SCORE": 3.8948,
      "ATLETA_ID": 98672
    },
    {
      "RODADA": 12,
      "TIPO": "ECONOMICO",
      "STATUS": "TITULAR",
      "POS": "MEI",
      "NOME": "Baralhas",
      "CLUBE": "VIT",
      "PRECO": 10.65,
      "EXP_SCORE": 4.2364,
      "ATLETA_ID": 99440
    },
    {
      "RODADA": 12,
      "TIPO": "ECONOMICO",
      "STATUS": "TITULAR",
      "POS": "ATA",
      "NOME": "Pedro",
      "CLUBE": "FLA",
      "PRECO": 18.6,
      "EXP_SCORE": 5.8804,
      "ATLETA_ID": 94583
    },
    {
      "RODADA": 12,
      "TIPO": "ECONOMICO",
      "STATUS": "TITULAR",
      "POS": "TEC",
      "NOME": "Rafael Guanaes",
      "CLUBE": "MIR",
      "PRECO": 6.71,
      "EXP_SCORE": 2.7734,
      "ATLETA_ID": 104027
    },
    {
      "RODADA": 12,
      "TIPO": "ECONOMICO",
      "STATUS": "RESERVA",
      "POS": "GOL",
      "NOME": "Pedro Rangel",
      "CLUBE": "CFC",
      "PRECO": 5.99,
      "EXP_SCORE": 3.3507,
      "ATLETA_ID": 110708
    },
    {
      "RODADA": 12,
      "TIPO": "ECONOMICO",
      "STATUS": "RESERVA",
      "POS": "LAT",
      "NOME": "Sant Anna",
      "CLUBE": "RBB",
      "PRECO": 9.23,
      "EXP_SCORE": 3.8616,
      "ATLETA_ID": 105213
    },
    {
      "RODADA": 12,
      "TIPO": "ECONOMICO",
      "STATUS": "RESERVA",
      "POS": "ZAG",
      "NOME": "Jacy",
      "CLUBE": "CFC",
      "PRECO": 4.95,
      "EXP_SCORE": 2.6371,
      "ATLETA_ID": 97878
    },
    {
      "RODADA": 12,
      "TIPO": "ECONOMICO",
      "STATUS": "RESERVA",
      "POS": "MEI",
      "NOME": "Monsalve",
      "CLUBE": "GRE",
      "PRECO": 2.71,
      "EXP_SCORE": 0.1475,
      "ATLETA_ID": 109966
    },
    {
      "RODADA": 12,
      "TIPO": "ECONOMICO",
      "STATUS": "RESERVA",
      "POS": "ATA",
      "NOME": "Lucas Barbosa",
      "CLUBE": "RBB",
      "PRECO": 9.42,
      "EXP_SCORE": 5.1199,
      "ATLETA_ID": 112886
    }
  ]
}