{
  "rodada": 7,
  "atualizado_em": "2026-03-17T23:47:40.529Z",
  "dados": [
    {
      "RODADA": 7,
      "POS": "GOL",
      "NOME": "Everson",
      "CLUBE": "CAM",
      "PRECO": 9.79,
      "EXP_SCORE": 3.7939,
      "FACTOR": 1.0900971476138934,
      "ATLETA_ID": 72294
    },
    {
      "RODADA": 7,
      "POS": "GOL",
      "NOME": "F?bio",
      "CLUBE": "FLU",
      "PRECO": 9.37,
      "EXP_SCORE": 3.2388,
      "FACTOR": 0.9986276178073972,
      "ATLETA_ID": 37656
    },
    {
      "RODADA": 7,
      "POS": "GOL",
      "NOME": "Ronaldo",
      "CLUBE": "BAH",
      "PRECO": 7.6,
      "EXP_SCORE": 3.0504,
      "FACTOR": 1.1699724007763512,
      "ATLETA_ID": 91101
    },
    {
      "RODADA": 7,
      "POS": "GOL",
      "NOME": "Santos",
      "CLUBE": "CAP",
      "PRECO": 10.29,
      "EXP_SCORE": 3.0051,
      "FACTOR": 1.167380806605947,
      "ATLETA_ID": 69012
    },
    {
      "RODADA": 7,
      "POS": "GOL",
      "NOME": "Carlos Miguel",
      "CLUBE": "PAL",
      "PRECO": 7.78,
      "EXP_SCORE": 2.9976,
      "FACTOR": 1.0997285946053956,
      "ATLETA_ID": 104084
    },
    {
      "RODADA": 7,
      "POS": "LAT",
      "NOME": "Luciano Juba",
      "CLUBE": "BAH",
      "PRECO": 9.87,
      "EXP_SCORE": 4.6815,
      "FACTOR": 1.1699724007763512,
      "ATLETA_ID": 107093
    },
    {
      "RODADA": 7,
      "POS": "LAT",
      "NOME": "Ren?",
      "CLUBE": "FLU",
      "PRECO": 11.38,
      "EXP_SCORE": 4.2942,
      "FACTOR": 0.9986276178073972,
      "ATLETA_ID": 78445
    },
    {
      "RODADA": 7,
      "POS": "LAT",
      "NOME": "Walter Clar",
      "CLUBE": "CHA",
      "PRECO": 8.54,
      "EXP_SCORE": 4.2408,
      "FACTOR": 1.1481565931329487,
      "ATLETA_ID": 105664
    },
    {
      "RODADA": 7,
      "POS": "LAT",
      "NOME": "Matheus Bidu",
      "CLUBE": "COR",
      "PRECO": 11.32,
      "EXP_SCORE": 3.7356,
      "FACTOR": 0.9701242262733087,
      "ATLETA_ID": 105531
    },
    {
      "RODADA": 7,
      "POS": "LAT",
      "NOME": "Cuiabano",
      "CLUBE": "VAS",
      "PRECO": 12.6,
      "EXP_SCORE": 3.732,
      "FACTOR": 1.0659218288601229,
      "ATLETA_ID": 116065
    },
    {
      "RODADA": 7,
      "POS": "ZAG",
      "NOME": "Gustavo G?mez",
      "CLUBE": "PAL",
      "PRECO": 11.39,
      "EXP_SCORE": 4.0847,
      "FACTOR": 1.0997285946053956,
      "ATLETA_ID": 71684
    },
    {
      "RODADA": 7,
      "POS": "ZAG",
      "NOME": "Sabino",
      "CLUBE": "SAO",
      "PRECO": 8.7,
      "EXP_SCORE": 3.3329,
      "FACTOR": 0.953061148152219,
      "ATLETA_ID": 104075
    },
    {
      "RODADA": 7,
      "POS": "ZAG",
      "NOME": "Gabriel Paulista",
      "CLUBE": "COR",
      "PRECO": 10.24,
      "EXP_SCORE": 3.1913,
      "FACTOR": 0.9701242262733087,
      "ATLETA_ID": 69208
    },
    {
      "RODADA": 7,
      "POS": "ZAG",
      "NOME": "Noriega",
      "CLUBE": "GRE",
      "PRECO": 7.12,
      "EXP_SCORE": 3.1816,
      "FACTOR": 1.094468045244575,
      "ATLETA_ID": 130048
    },
    {
      "RODADA": 7,
      "POS": "ZAG",
      "NOME": "L?o Pereira",
      "CLUBE": "FLA",
      "PRECO": 12.28,
      "EXP_SCORE": 2.9151,
      "FACTOR": 1.1056853931463246,
      "ATLETA_ID": 83528
    },
    {
      "RODADA": 7,
      "POS": "MEI",
      "NOME": "Lucho Acosta",
      "CLUBE": "FLU",
      "PRECO": 12.77,
      "EXP_SCORE": 5.3277,
      "FACTOR": 0.9659457262583936,
      "ATLETA_ID": 89837
    },
    {
      "RODADA": 7,
      "POS": "MEI",
      "NOME": "Andreas Pereira",
      "CLUBE": "PAL",
      "PRECO": 14.05,
      "EXP_SCORE": 5.0822,
      "FACTOR": 1.1242349068511133,
      "ATLETA_ID": 89274
    },
    {
      "RODADA": 7,
      "POS": "MEI",
      "NOME": "Danilo",
      "CLUBE": "BOT",
      "PRECO": 14.95,
      "EXP_SCORE": 4.2713,
      "FACTOR": 0.9210309234109153,
      "ATLETA_ID": 107231
    },
    {
      "RODADA": 7,
      "POS": "MEI",
      "NOME": "Neymar",
      "CLUBE": "SAN",
      "PRECO": 22.31,
      "EXP_SCORE": 3.8562,
      "FACTOR": 1.1488943706770334,
      "ATLETA_ID": 63007
    },
    {
      "RODADA": 7,
      "POS": "MEI",
      "NOME": "Jean Carlos",
      "CLUBE": "CHA",
      "PRECO": 9.04,
      "EXP_SCORE": 3.5812,
      "FACTOR": 0.9972570707325692,
      "ATLETA_ID": 70958
    },
    {
      "RODADA": 7,
      "POS": "ATA",
      "NOME": "Lucas Ronier",
      "CLUBE": "CFC",
      "PRECO": 10.74,
      "EXP_SCORE": 7.285,
      "FACTOR": 1.0106662795981218,
      "ATLETA_ID": 123648
    },
    {
      "RODADA": 7,
      "POS": "ATA",
      "NOME": "Pedro",
      "CLUBE": "FLA",
      "PRECO": 19.02,
      "EXP_SCORE": 5.1055,
      "FACTOR": 1.184791679709194,
      "ATLETA_ID": 94583
    },
    {
      "RODADA": 7,
      "POS": "ATA",
      "NOME": "Andr?s G?mez",
      "CLUBE": "VAS",
      "PRECO": 11.7,
      "EXP_SCORE": 4.9253,
      "FACTOR": 1.0064583632049275,
      "ATLETA_ID": 116706
    },
    {
      "RODADA": 7,
      "POS": "ATA",
      "NOME": "Carlos Vin?cius",
      "CLUBE": "GRE",
      "PRECO": 16.48,
      "EXP_SCORE": 4.5839,
      "FACTOR": 0.9727939011460596,
      "ATLETA_ID": 105563
    },
    {
      "RODADA": 7,
      "POS": "ATA",
      "NOME": "Flaco L?pez",
      "CLUBE": "PAL",
      "PRECO": 15.67,
      "EXP_SCORE": 4.4796,
      "FACTOR": 1.1242349068511133,
      "ATLETA_ID": 113103
    },
    {
      "RODADA": 7,
      "POS": "TEC",
      "NOME": "Abel Ferreira",
      "CLUBE": "PAL",
      "PRECO": 12.18,
      "EXP_SCORE": 4.5808,
      "FACTOR": 1.0930061594385825,
      "ATLETA_ID": 110506
    },
    {
      "RODADA": 7,
      "POS": "TEC",
      "NOME": "Luis Zubeld?a",
      "CLUBE": "FLU",
      "PRECO": 10.36,
      "EXP_SCORE": 3.8882,
      "FACTOR": 0.9862814257585703,
      "ATLETA_ID": 99366
    },
    {
      "RODADA": 7,
      "POS": "TEC",
      "NOME": "Fernando Seabra",
      "CLUBE": "CFC",
      "PRECO": 7.63,
      "EXP_SCORE": 3.7795,
      "FACTOR": 1.0319434644317667,
      "ATLETA_ID": 126977
    },
    {
      "RODADA": 7,
      "POS": "TEC",
      "NOME": "Rog?rio Ceni",
      "CLUBE": "BAH",
      "PRECO": 10.77,
      "EXP_SCORE": 3.7028,
      "FACTOR": 1.1317470086333115,
      "ATLETA_ID": 97341
    },
    {
      "RODADA": 7,
      "POS": "TEC",
      "NOME": "Leonardo Jardim",
      "CLUBE": "FLA",
      "PRECO": 14.76,
      "EXP_SCORE": 3.5219,
      "FACTOR": 1.1518807997172718,
      "ATLETA_ID": 88963
    }
  ]
}